object_freezer/__init__.py
object_freezer/core.py
object_freezer/freezeargs.py
object_freezer-0.1.2.dist-info/LICENSE
object_freezer-0.1.2.dist-info/METADATA
object_freezer-0.1.2.dist-info/WHEEL
object_freezer-0.1.2.dist-info/top_level.txt
object_freezer-0.1.2.dist-info/RECORD
