Metadata-Version: 2.1
Name: object-freezer
Version: 0.1.2
Summary: Python module for freezing objects
Home-page: https://github.com/shunichironomura/freezer
Author: Shunichiro Nomura
Author-email: nomura@space.t.u-tokyo.ac.jp
License: MIT
Download-URL: https://github.com/shunichironomura/object-freezer/archive/v0.1.1.tar.gz
Platform: UNKNOWN
Classifier: Development Status :: 4 - Beta
Classifier: Intended Audience :: Developers
Classifier: License :: OSI Approved :: MIT License
Classifier: Programming Language :: Python :: 3
Classifier: Programming Language :: Python :: 3.6
